{
	"caso1descricao": ["Uma mulher solitária se joga de um edificio comercial. No instante em que pula, e está no ar em quedra livre, ela se arrepende de ter pulado, mas já era tarde demais."],
	"caso1perguntas": ["A mulher achava que era a única sobrevivente de um acidente .................... ", "Ela vagou feito alma penada por um ano por toda a .................... ", "No auge na sua depressão, ela decidiu se .................... ", "Ela então sobe no topo de um .................... ", "Ao se jogar, ela descobre não ser a única sobrevivente, pois ouve um .................... ", "Sem dúvida havia outro .................... "],
	"caso1respostas": ["nuclear", "cidade", "matar", "prédio", "telefone"],
	"caso1pistafinal": ["sobrevivente"],
	"caso2descricao": ["Um pesquisador inocente é assassinado a caminho de um órgão público."],
	"caso2perguntas": ["O homem fez um invento incrível e saiu para registrar uma ....................", "Ele inventara um motor que funciona somente à base de ....................", "Sua descoberta representaria o fim da indústria de ....................", "Multinacionais queriam que ele abandonasse o invento e lhe ofereceram uma ....................", "O homem recusou a oferta, então os grandes empresários apelaram para o ....................", "Quem contratou o assassino foram as multinacionais ...................."],
	"caso2respostas": ["patente", "água", "petróleo", "fortuna", "assassinato"],
	"caso2pistafinal": ["petrolíferas"],
	"caso3descricao": [""],
	"caso3perguntas": ["", "", "", "", "", ""],
	"caso3respostas": ["", "", "", "", ""],
	"caso3pistafinal": [""]
}